campfire_api/__init__.py
campfire_api/api.py
campfire_api/errors.py
campfire_api/post_elements.py
campfire_api/tools.py
Campfire_API-0.0.7.dist-info/LICENSE
Campfire_API-0.0.7.dist-info/METADATA
Campfire_API-0.0.7.dist-info/WHEEL
Campfire_API-0.0.7.dist-info/top_level.txt
Campfire_API-0.0.7.dist-info/RECORD
