Metadata-Version: 2.1
Name: Campfire-API
Version: 0.0.7
Summary: CampfireAPI based on Capfire web.
Home-page: https://github.com/Ghost-3/CapfireAPI
Author: Ghost-3
Author-email: ghost3.github@gmail.com
License: UNKNOWN
Platform: UNKNOWN
Classifier: Programming Language :: Python :: 3.8
Classifier: License :: OSI Approved :: MIT License
Classifier: Operating System :: OS Independent
Requires-Python: >=3.6
License-File: LICENSE
Requires-Dist: requests (<=2.26.0)
